TOPSIS/__init__.py
TOPSIS/__main__.py
TOPSIS_Divya_101953024-1.0.1.dist-info/METADATA
TOPSIS_Divya_101953024-1.0.1.dist-info/WHEEL
TOPSIS_Divya_101953024-1.0.1.dist-info/entry_points.txt
TOPSIS_Divya_101953024-1.0.1.dist-info/top_level.txt
TOPSIS_Divya_101953024-1.0.1.dist-info/RECORD
