Metadata-Version: 2.1
Name: TOPSIS-Divya-101953024
Version: 1.0.1
Summary: TOPSIS
Home-page: UNKNOWN
Author: Divya Goel
Author-email: divyaji.goel@gmail.com
License: MIT
Platform: UNKNOWN
Classifier: License :: OSI Approved :: MIT License
Classifier: Programming Language :: Python :: 3.6
Classifier: Programming Language :: Python :: 3.7
Classifier: Programming Language :: Python :: 3.8
